confusion_hunter/Architecture.md
confusion_hunter/__init__.py
confusion_hunter/__main__.py
confusion_hunter/manager.py
confusion_hunter/scanner.py
confusion_hunter/detectors/__init__.py
confusion_hunter/detectors/base.py
confusion_hunter/detectors/schema_loader.py
confusion_hunter/detectors/schemas/javascript_detector.json
confusion_hunter/detectors/schemas/maven_detector.json
confusion_hunter/detectors/schemas/npm_install_detector.json
confusion_hunter/detectors/schemas/pip_install_detector.json
confusion_hunter/detectors/schemas/python_detector.json
confusion_hunter/executors/__init__.py
confusion_hunter/executors/base.py
confusion_hunter/executors/buildgradle_executor.py
confusion_hunter/executors/maven_package_list_executor.py
confusion_hunter/executors/npm_install_executor.py
confusion_hunter/executors/npm_package_list_executor.py
confusion_hunter/executors/package_json_executor.py
confusion_hunter/executors/pip_freeze_executor.py
confusion_hunter/executors/pip_install_executor.py
confusion_hunter/executors/pipfile_executor.py
confusion_hunter/executors/poetry_lock_executor.py
confusion_hunter/executors/pyproject_executor.py
confusion_hunter/executors/requirements_executor.py
confusion_hunter/executors/uv_lock_executor.py
confusion_hunter/executors/package_parsers/__init__.py
confusion_hunter/executors/package_parsers/all_possiblilities.md
confusion_hunter/executors/package_parsers/base.py
confusion_hunter/executors/package_parsers/buildgradle_parser.py
confusion_hunter/executors/package_parsers/npm_parser.py
confusion_hunter/executors/package_parsers/pip_parser.py
confusion_hunter/executors/package_parsers/pipfile_parser.py
confusion_hunter/executors/package_parsers/poetry_parser.py
confusion_hunter/executors/package_parsers/pomxml_parser.py
confusion_hunter/executors/package_parsers/pyproject_parser.py
confusion_hunter/executors/package_parsers/uv_parser.py
confusion_hunter/executors/package_parsers/tests/conftest.py
confusion_hunter-0.1.1.dist-info/METADATA
confusion_hunter-0.1.1.dist-info/WHEEL
confusion_hunter-0.1.1.dist-info/entry_points.txt
confusion_hunter-0.1.1.dist-info/licenses/LICENSE
confusion_hunter-0.1.1.dist-info/RECORD
