Metadata-Version: 2.4
Name: confusion-hunter
Version: 0.1.1
Summary: Lightweight scanner for spotting unclaimed dependencies before attackers do - protects against supply-chain attacks
Project-URL: Homepage, https://github.com/seznam/confusion-hunter
Project-URL: Documentation, https://github.com/seznam/confusion-hunter#readme
Author-email: Seznam Security Team <security@firma.seznam.cz>
Maintainer-email: Seznam Security Team <security@firma.seznam.cz>
License: MIT
License-File: LICENSE
Keywords: dependencies,dependency-confusion,maven,npm,pypi,sarif,security,supply-chain,vulnerability-scanner
Classifier: Development Status :: 4 - Beta
Classifier: Environment :: Console
Classifier: Intended Audience :: Developers
Classifier: Intended Audience :: System Administrators
Classifier: License :: OSI Approved :: MIT License
Classifier: Operating System :: OS Independent
Classifier: Programming Language :: Python :: 3
Classifier: Programming Language :: Python :: 3.10
Classifier: Programming Language :: Python :: 3.11
Classifier: Programming Language :: Python :: 3.12
Classifier: Programming Language :: Python :: 3.13
Classifier: Topic :: Security
Classifier: Topic :: Software Development :: Quality Assurance
Classifier: Topic :: System :: Systems Administration
Requires-Python: >=3.10
Requires-Dist: aiohttp>=3.8.0
Requires-Dist: aiolimiter>=1.0.0
Requires-Dist: async-timeout>=4.0.0
Requires-Dist: bashlex>=0.16
Requires-Dist: packaging>=21.0
Requires-Dist: requests>=2.25.0
Requires-Dist: tenacity>=8.0.0
Requires-Dist: typing-extensions>=4.0.0
Provides-Extra: test
Requires-Dist: pytest; extra == 'test'
Requires-Dist: sarif-pydantic; extra == 'test'
